eniam/__init__.py
eniam/eniam_core.py
eniam/eniam_syntax.py
eniam/lol.py
eniam-1.0.data/scripts/eniam-cli
eniam_src/__init__.py
eniam_src/tools/__init__.py
eniam_src/tools/concraft2/__init__.py
eniam_src/tools/concraft2/concrafteusz.py
eniam_src/tools/concraft2/tageruj.py
eniam_src/tools/swigra/__init__.py
eniam_src/tools/swigra/disambiguator-pcfg/__init__.py
eniam_src/tools/swigra/disambiguator-pcfg/disamb-tree.py
eniam_src/tools/swigra/disambiguator-pcfg/main-main-mistake.py
eniam_src/tools/swigra/disambiguator-pcfg/make-model.py
eniam_src/tools/swigra/disambiguator-pcfg/node.py
eniam_src/tools/swigra/disambiguator-pcfg/productionparseractpcfg.py
eniam_src/tools/swigra/disambiguator-pcfg/tree.py
eniam_src/tools/swigra/disambiguator-pcfg/treeparser.py
eniam_src/tools/wosedon/__init__.py
eniam_src/tools/wosedon/CclExtractor/__init__.py
eniam_src/tools/wosedon/CclExtractor/setup.py
eniam_src/tools/wosedon/CclExtractor/CclExtractor/CclExtractor.py
eniam_src/tools/wosedon/CclExtractor/CclExtractor/__init__.py
eniam_src/tools/wosedon/PLWNGraphBuilder/__init__.py
eniam_src/tools/wosedon/PLWNGraphBuilder/setup.py
eniam_src/tools/wosedon/PLWNGraphBuilder/PLWNGraphBuilder/PLWNGraphBuilder.py
eniam_src/tools/wosedon/PLWNGraphBuilder/PLWNGraphBuilder/__init__.py
eniam_src/tools/wosedon/PLWNGraphBuilder/PLWNGraphBuilder/plwn_graph_new.py
eniam_src/tools/wosedon/PLWNGraphBuilder/PLWNGraphBuilder/plwn_graph_old.py
eniam_src/tools/wosedon/PLWNGraphBuilder/PLWNGraphBuilder/vertices/__init__.py
eniam_src/tools/wosedon/PLWNGraphBuilder/PLWNGraphBuilder/vertices/lexical_unit.py
eniam_src/tools/wosedon/PLWNGraphBuilder/PLWNGraphBuilder/vertices/synset.py
eniam_src/tools/wosedon/PLWNGraphBuilder/build/__init__.py
eniam_src/tools/wosedon/Resolver/__init__.py
eniam_src/tools/wosedon/Resolver/setup.py
eniam_src/tools/wosedon/Resolver/Resolver/Resolver.py
eniam_src/tools/wosedon/Resolver/Resolver/__init__.py
eniam_src/tools/wosedon/tools/__init__.py
eniam-1.0.dist-info/METADATA
eniam-1.0.dist-info/WHEEL
eniam-1.0.dist-info/top_level.txt
eniam-1.0.dist-info/RECORD
