Metadata-Version: 2.1
Name: eniam
Version: 1.0
Summary: Cross-platform python wrapper around ENIAM (http://eniam.nlp.ipipan.waw.pl/)
Home-page: http://styczynski.in
Author: styczynski
Author-email: piotr@styczynski.in
License: MIT
Platform: UNKNOWN
Requires-Dist: opencv-python (==4.2.0.32)
Requires-Dist: camelot-py (==0.7.2)
Requires-Dist: wand (==0.5.8)
Requires-Dist: beautifulsoup4 (==4.9.0)
